markdown_code_blocks.py
markdown_code_blocks-3.1.0.dist-info/LICENSE
markdown_code_blocks-3.1.0.dist-info/METADATA
markdown_code_blocks-3.1.0.dist-info/WHEEL
markdown_code_blocks-3.1.0.dist-info/entry_points.txt
markdown_code_blocks-3.1.0.dist-info/top_level.txt
markdown_code_blocks-3.1.0.dist-info/RECORD
